harmonicsradius/hri95.py
harmonicsradius/image.py
harmonicsradius/preprocessors.py
harmonicsradius/settings.py
harmonicsradius/sr_analyzer.py
harmonicsradius/utils.py
harmonicsradius/metrics/__init__.py
harmonicsradius/metrics/harmonics_radius.py
harmonicsradius/metrics/interface_metric.py
harmonicsradius/metrics/mean_squared_error.py
harmonicsradius/metrics/peak_signal_to_noise_ratio.py
harmonicsradius/metrics/structural_similarity_index.py
harmonicsradius-2024.5.22.dist-info/LICENSE
harmonicsradius-2024.5.22.dist-info/METADATA
harmonicsradius-2024.5.22.dist-info/WHEEL
harmonicsradius-2024.5.22.dist-info/entry_points.txt
harmonicsradius-2024.5.22.dist-info/top_level.txt
harmonicsradius-2024.5.22.dist-info/RECORD
