Metadata-Version: 2.1
Name: harmonicsradius
Version: 2024.5.22
Summary: Harmonics' Radius Index (HRI95) is a full-reference image quality index based harmonic structures of the images for the comparison super-resolution models.
Author-email: Gökhan Koçmarlı <gokhan.kocmarli@gmail.com>
Maintainer-email: Gökhan Koçmarlı <gokhan.kocmarli@gmail.com>
License: GNU GENERAL PUBLIC LICENSE
Project-URL: Homepage, https://github.com/electricalgorithm/universal-hri95
Project-URL: Repository, https://github.com/electricalgorithm/universal-hri95.git
Project-URL: Issues, https://github.com/electricalgorithm/universal-hri95/issues
Keywords: super-resolution,frequency-analysis,image-quality-metrics
Classifier: Development Status :: 5 - Production/Stable
Classifier: Intended Audience :: Information Technology
Classifier: Intended Audience :: Other Audience
Classifier: Topic :: Scientific/Engineering :: Image Processing
Classifier: License :: OSI Approved :: GNU General Public License v3 (GPLv3)
Classifier: Programming Language :: Python :: 3.10
Classifier: Programming Language :: Python :: 3.11
Requires-Python: >=3.10
License-File: LICENSE
Requires-Dist: numpy
Requires-Dist: opencv-python
Requires-Dist: scikit-image
